parea/__init__.py
parea/api_client.py
parea/cache/__init__.py
parea/cache/cache.py
parea/cache/in_memory.py
parea/client.py
parea/constants.py
parea/evals/__init__.py
parea/evals/chat/__init__.py
parea/evals/chat/goal_success_ratio.py
parea/evals/dataset_level/__init__.py
parea/evals/dataset_level/balanced_acc.py
parea/evals/general/__init__.py
parea/evals/general/answer_matches_target_llm_grader.py
parea/evals/general/answer_matches_target_recall.py
parea/evals/general/answer_relevancy.py
parea/evals/general/levenshtein.py
parea/evals/general/llm_grader.py
parea/evals/general/lm_vs_lm.py
parea/evals/general/self_check.py
parea/evals/general/semantic_similarity.py
parea/evals/rag/__init__.py
parea/evals/rag/answer_context_faithfulness_binary.py
parea/evals/rag/answer_context_faithfulness_precision.py
parea/evals/rag/answer_context_faithfulness_statement_level.py
parea/evals/rag/context_has_answer.py
parea/evals/rag/context_query_relevancy.py
parea/evals/rag/context_ranking_listwise.py
parea/evals/rag/context_ranking_pointwise.py
parea/evals/rag/percent_target_supported_by_context.py
parea/evals/summary/__init__.py
parea/evals/summary/factual_inconsistency_binary.py
parea/evals/summary/factual_inconsistency_scale.py
parea/evals/summary/likert_scale.py
parea/evals/utils.py
parea/experiment/__init__.py
parea/experiment/cli.py
parea/experiment/datasets.py
parea/experiment/dvc.py
parea/experiment/experiment.py
parea/helpers.py
parea/parea_logger.py
parea/schemas/__init__.py
parea/schemas/log.py
parea/schemas/models.py
parea/types.py
parea/utils/__init__.py
parea/utils/trace_integrations/dspy.py
parea/utils/trace_integrations/instructor.py
parea/utils/trace_integrations/langchain.py
parea/utils/trace_integrations/langchain_utils.py
parea/utils/trace_integrations/wrapt_utils.py
parea/utils/trace_utils.py
parea/utils/universal_encoder.py
parea/wrapper/__init__.py
parea/wrapper/anthropic/__init__.py
parea/wrapper/anthropic/anthropic.py
parea_ai-0.2.219.dist-info/LICENSE
parea_ai-0.2.219.dist-info/METADATA
parea_ai-0.2.219.dist-info/WHEEL
parea_ai-0.2.219.dist-info/entry_points.txt
parea_ai-0.2.219.dist-info/RECORD
