Metadata-Version: 2.1
Name: parea-ai
Version: 0.2.219
Summary: Parea python sdk
Home-page: https://github.com/parea-ai/parea-sdk
License: Apache Software License 2.0
Author: joel-parea-ai
Author-email: joel@parea.ai
Requires-Python: >=3.9,<4.0
Classifier: Development Status :: 3 - Alpha
Classifier: Intended Audience :: Developers
Classifier: License :: OSI Approved :: Apache Software License
Classifier: License :: Other/Proprietary License
Classifier: Operating System :: OS Independent
Classifier: Programming Language :: Python :: 3
Classifier: Programming Language :: Python :: 3.9
Classifier: Programming Language :: Python :: 3.10
Classifier: Programming Language :: Python :: 3.11
Classifier: Programming Language :: Python :: 3.12
Classifier: Topic :: Software Development :: Libraries :: Python Modules
Requires-Dist: cattrs (>=22.1.0)
Requires-Dist: contextvars (>=2.4,<3.0)
Requires-Dist: httpx (>=0.28.1)
Requires-Dist: levenshtein (>=0.26.1,<0.27.0)
Requires-Dist: openai
Requires-Dist: orjson (>=3.10.14,<4.0.0)
Requires-Dist: poetry-plugin-dotenv (>=2.6.1,<3.0.0)
Requires-Dist: pysbd (>=0.3.4,<0.4.0)
Requires-Dist: python-dotenv (>=1.0.1,<2.0.0)
Requires-Dist: pytz (>=2024.2,<2025.0)
Requires-Dist: pyupgrade (>=3.19.1,<4.0.0)
Requires-Dist: tenacity
Requires-Dist: tiktoken (>=0.5.2)
Requires-Dist: wrapt (>=1.17.2,<2.0.0)
Project-URL: Repository, https://github.com/parea-ai/parea-sdk
